telegram_bot_utils/__init__.py
telegram_bot_utils/core/__init__.py
telegram_bot_utils/core/interaction/__init__.py
telegram_bot_utils/core/interaction/abstract_handler.py
telegram_bot_utils/core/interaction/handlers/__init__.py
telegram_bot_utils/core/interaction/handlers/callback_decorator.py
telegram_bot_utils/core/interaction/handlers/dispatcher_message_handler.py
telegram_bot_utils/core/interaction/handlers/callbacks/__init__.py
telegram_bot_utils/core/interaction/handlers/callbacks/abstract_callback_handler.py
telegram_bot_utils/core/interaction/menus/__init__.py
telegram_bot_utils/core/interaction/menus/abstract_menu.py
telegram_bot_utils/core/utils/__init__.py
telegram_bot_utils/core/utils/banner_utils.py
telegram_bot_utils/core/utils/validation.py
telegram_bot_utils-0.0.6.dist-info/METADATA
telegram_bot_utils-0.0.6.dist-info/WHEEL
telegram_bot_utils-0.0.6.dist-info/top_level.txt
telegram_bot_utils-0.0.6.dist-info/RECORD
