Metadata-Version: 2.2
Name: telegram-bot-utils
Version: 0.0.6
Summary: Engine for web3 smart contracts automatization.
Author-email: Indeoo <indeooars@gmail.com>
License: MIT
Project-URL: Homepage, https://github.com/Indeoo/market-analyzer/
Requires-Python: >=3.9
Requires-Dist: alembic==1.14.0
Requires-Dist: asyncpg==0.30.0
Requires-Dist: python-telegram-bot==21.7
